{
  "generated_at": "2026-07-15T09:27:29",
  "season": 2026,
  "player_count": 0,
  "projections": [
    {
      "name": "Cal Raleigh",
      "mlb_id": 663728,
      "positions": [
        "C",
        "DH"
      ],
      "status": "no_game",
      "proj_pts": null,
      "confidence": null,
      "stat_line": null,
      "factors": [],
      "pitch_rows": [],
      "note": "No game scheduled today",
      "rank": null
    },
    {
      "name": "Sal Stewart",
      "mlb_id": 701398,
      "positions": [
        "1B",
        "3B"
      ],
      "status": "no_game",
      "proj_pts": null,
      "confidence": null,
      "stat_line": null,
      "factors": [],
      "pitch_rows": [],
      "note": "No game scheduled today",
      "rank": null
    },
    {
      "name": "Ketel Marte",
      "mlb_id": 606466,
      "positions": [
        "2B",
        "DH"
      ],
      "status": "no_game",
      "proj_pts": null,
      "confidence": null,
      "stat_line": null,
      "factors": [],
      "pitch_rows": [],
      "note": "No game scheduled today",
      "rank": null
    },
    {
      "name": "Josh Jung",
      "mlb_id": 673962,
      "positions": [
        "3B"
      ],
      "status": "no_game",
      "proj_pts": null,
      "confidence": null,
      "stat_line": null,
      "factors": [],
      "pitch_rows": [],
      "note": "No game scheduled today",
      "rank": null
    },
    {
      "name": "Geraldo Perdomo",
      "mlb_id": 672695,
      "positions": [
        "SS"
      ],
      "status": "no_game",
      "proj_pts": null,
      "confidence": null,
      "stat_line": null,
      "factors": [],
      "pitch_rows": [],
      "note": "No game scheduled today",
      "rank": null
    },
    {
      "name": "Mickey Moniak",
      "mlb_id": 666160,
      "positions": [
        "CF",
        "LF",
        "RF"
      ],
      "status": "no_game",
      "proj_pts": null,
      "confidence": null,
      "stat_line": null,
      "factors": [],
      "pitch_rows": [],
      "note": "No game scheduled today",
      "rank": null
    },
    {
      "name": "Alejandro Kirk",
      "mlb_id": 672386,
      "positions": [
        "C"
      ],
      "status": "no_game",
      "proj_pts": null,
      "confidence": null,
      "stat_line": null,
      "factors": [],
      "pitch_rows": [],
      "note": "No game scheduled today",
      "rank": null
    },
    {
      "name": "Michael Busch",
      "mlb_id": 683737,
      "positions": [
        "1B"
      ],
      "status": "no_game",
      "proj_pts": null,
      "confidence": null,
      "stat_line": null,
      "factors": [],
      "pitch_rows": [],
      "note": "No game scheduled today",
      "rank": null
    },
    {
      "name": "Manny Machado",
      "mlb_id": 592518,
      "positions": [
        "3B"
      ],
      "status": "no_game",
      "proj_pts": null,
      "confidence": null,
      "stat_line": null,
      "factors": [],
      "pitch_rows": [],
      "note": "No game scheduled today",
      "rank": null
    },
    {
      "name": "Kody Clemens",
      "mlb_id": 665019,
      "positions": [
        "1B, 2B, LF"
      ],
      "status": "no_game",
      "proj_pts": null,
      "confidence": null,
      "stat_line": null,
      "factors": [],
      "pitch_rows": [],
      "note": "No game scheduled today",
      "rank": null
    },
    {
      "name": "Esmerlyn Valdez",
      "mlb_id": 699013,
      "positions": [
        "RF, DH"
      ],
      "status": "no_game",
      "proj_pts": null,
      "confidence": null,
      "stat_line": null,
      "factors": [],
      "pitch_rows": [],
      "note": "No game scheduled today",
      "rank": null
    },
    {
      "name": "Lars Nootbaar",
      "mlb_id": 663457,
      "positions": [
        "LF, RF"
      ],
      "status": "no_game",
      "proj_pts": null,
      "confidence": null,
      "stat_line": null,
      "factors": [],
      "pitch_rows": [],
      "note": "No game scheduled today",
      "rank": null
    },
    {
      "name": "Jake McCarthy",
      "mlb_id": 664983,
      "positions": [
        "CF",
        "LF"
      ],
      "status": "no_game",
      "proj_pts": null,
      "confidence": null,
      "stat_line": null,
      "factors": [],
      "pitch_rows": [],
      "note": "No game scheduled today",
      "rank": null
    },
    {
      "name": "Aaron Judge",
      "mlb_id": 592450,
      "positions": [
        "RF",
        "DH"
      ],
      "status": "il10",
      "proj_pts": null,
      "confidence": null,
      "stat_line": null,
      "factors": [],
      "pitch_rows": [],
      "rank": null
    },
    {
      "name": "Addison Barger",
      "mlb_id": 680718,
      "positions": [
        "3B",
        "RF"
      ],
      "status": "il10",
      "proj_pts": null,
      "confidence": null,
      "stat_line": null,
      "factors": [],
      "pitch_rows": [],
      "rank": null
    }
  ],
  "projections_historical": [
    {
      "name": "Cal Raleigh",
      "mlb_id": 663728,
      "status": "no_game",
      "proj_pts": null,
      "proj_low": null,
      "proj_high": null,
      "model": "historical"
    },
    {
      "name": "Sal Stewart",
      "mlb_id": 701398,
      "status": "no_game",
      "proj_pts": null,
      "proj_low": null,
      "proj_high": null,
      "model": "historical"
    },
    {
      "name": "Ketel Marte",
      "mlb_id": 606466,
      "status": "no_game",
      "proj_pts": null,
      "proj_low": null,
      "proj_high": null,
      "model": "historical"
    },
    {
      "name": "Josh Jung",
      "mlb_id": 673962,
      "status": "no_game",
      "proj_pts": null,
      "proj_low": null,
      "proj_high": null,
      "model": "historical"
    },
    {
      "name": "Geraldo Perdomo",
      "mlb_id": 672695,
      "status": "no_game",
      "proj_pts": null,
      "proj_low": null,
      "proj_high": null,
      "model": "historical"
    },
    {
      "name": "Mickey Moniak",
      "mlb_id": 666160,
      "status": "no_game",
      "proj_pts": null,
      "proj_low": null,
      "proj_high": null,
      "model": "historical"
    },
    {
      "name": "Alejandro Kirk",
      "mlb_id": 672386,
      "status": "no_game",
      "proj_pts": null,
      "proj_low": null,
      "proj_high": null,
      "model": "historical"
    },
    {
      "name": "Michael Busch",
      "mlb_id": 683737,
      "status": "no_game",
      "proj_pts": null,
      "proj_low": null,
      "proj_high": null,
      "model": "historical"
    },
    {
      "name": "Manny Machado",
      "mlb_id": 592518,
      "status": "no_game",
      "proj_pts": null,
      "proj_low": null,
      "proj_high": null,
      "model": "historical"
    },
    {
      "name": "Kody Clemens",
      "mlb_id": 665019,
      "status": "no_game",
      "proj_pts": null,
      "proj_low": null,
      "proj_high": null,
      "model": "historical"
    },
    {
      "name": "Esmerlyn Valdez",
      "mlb_id": 699013,
      "status": "no_game",
      "proj_pts": null,
      "proj_low": null,
      "proj_high": null,
      "model": "historical"
    },
    {
      "name": "Lars Nootbaar",
      "mlb_id": 663457,
      "status": "no_game",
      "proj_pts": null,
      "proj_low": null,
      "proj_high": null,
      "model": "historical"
    },
    {
      "name": "Jake McCarthy",
      "mlb_id": 664983,
      "status": "no_game",
      "proj_pts": null,
      "proj_low": null,
      "proj_high": null,
      "model": "historical"
    },
    {
      "name": "Aaron Judge",
      "mlb_id": 592450,
      "positions": [
        "RF",
        "DH"
      ],
      "status": "il10",
      "proj_pts": null,
      "proj_low": null,
      "proj_high": null,
      "model": "historical"
    },
    {
      "name": "Addison Barger",
      "mlb_id": 680718,
      "positions": [
        "3B",
        "RF"
      ],
      "status": "il10",
      "proj_pts": null,
      "proj_low": null,
      "proj_high": null,
      "model": "historical"
    }
  ],
  "lineup_mc": {
    "probs": {},
    "n_sim": 10000,
    "n_starters": 0
  }
}